z_test_poetry/__init__.py
z_test_poetry/module_1.py
z_test_poetry/module_2.py
z_test_poetry-0.1.0.dist-info/METADATA
z_test_poetry-0.1.0.dist-info/WHEEL
z_test_poetry-0.1.0.dist-info/RECORD
